adafruit_circuitpython_is31fl3731-3.4.6.dist-info/licenses/LICENSE
adafruit_is31fl3731/__init__.py
adafruit_is31fl3731/charlie_bonnet.py
adafruit_is31fl3731/charlie_wing.py
adafruit_is31fl3731/keybow2040.py
adafruit_is31fl3731/led_shim.py
adafruit_is31fl3731/matrix.py
adafruit_is31fl3731/matrix_11x7.py
adafruit_is31fl3731/rgbmatrix5x5.py
adafruit_is31fl3731/scroll_phat_hd.py
adafruit_circuitpython_is31fl3731-3.4.6.dist-info/METADATA
adafruit_circuitpython_is31fl3731-3.4.6.dist-info/WHEEL
adafruit_circuitpython_is31fl3731-3.4.6.dist-info/top_level.txt
adafruit_circuitpython_is31fl3731-3.4.6.dist-info/RECORD
