Metadata-Version: 2.4
Name: adafruit-circuitpython-is31fl3731
Version: 3.4.6
Summary: CircuitPython library for IS31FL3731 charlieplex LED matrices.
Author-email: Adafruit Industries <circuitpython@adafruit.com>
License: MIT
Project-URL: Homepage, https://github.com/adafruit/Adafruit_CircuitPython_IS31FL3731
Keywords: adafruit,is31fl3731,led,matrix,charlieplex,featherwingbreakout,hardware,micropython,circuitpython
Classifier: Intended Audience :: Developers
Classifier: Topic :: Software Development :: Libraries
Classifier: Topic :: Software Development :: Embedded Systems
Classifier: Topic :: System :: Hardware
Classifier: License :: OSI Approved :: MIT License
Classifier: Programming Language :: Python :: 3
License-File: LICENSE
Requires-Dist: Adafruit-Blinka
Requires-Dist: adafruit-circuitpython-busdevice
Provides-Extra: optional
Requires-Dist: adafruit-circuitpython-framebuf; extra == "optional"
Requires-Dist: pillow; extra == "optional"
Dynamic: license-file
